.gitignore
README.rst
setup.py
examples/arrayimage_display.py
pygarrayimage/__init__.py
pygarrayimage/arrayimage.py
pygarrayimage.egg-info/.gitignore
pygarrayimage.egg-info/PKG-INFO
pygarrayimage.egg-info/SOURCES.txt
pygarrayimage.egg-info/dependency_links.txt
pygarrayimage.egg-info/stdeb.cfg
pygarrayimage.egg-info/top_level.txt