Metadata-Version: 1.0
Name: pygarrayimage
Version: 1.0
Summary: Allow numpy arrays as source of texture data for pyglet.
Home-page: http://code.astraw.com/projects/motmot/wiki/pygarrayimage
Author: Andrew Straw
Author-email: strawman@astraw.com
License: BSD
Platform: UNKNOWN
